mongoengine2excel/__init__.py
mongoengine2excel/convert.py
mongoengine2excel/iterator2excel.py
mongoengine2excel/mongo2excel.py
mongoengine2excel/transform.py
mongoengine2excel/utils.py
mongoengine2excel-1.1.2.dist-info/AUTHORS
mongoengine2excel-1.1.2.dist-info/METADATA
mongoengine2excel-1.1.2.dist-info/WHEEL
mongoengine2excel-1.1.2.dist-info/pbr.json
mongoengine2excel-1.1.2.dist-info/top_level.txt
mongoengine2excel-1.1.2.dist-info/RECORD
